{
    "512x512": {
        "count": 123,
        "indices": [
            18,
            28,
            63,
            65,
            76,
            77,
            88,
            97,
            98,
            128,
            133,
            142,
            145,
            152,
            154,
            157,
            187,
            188,
            214,
            220,
            269,
            330,
            372,
            434,
            567,
            599,
            606,
            863,
            961,
            989,
            1197,
            1251,
            1432,
            1433,
            1479,
            1582,
            1659,
            1660,
            1738,
            1739,
            1782,
            1783,
            1851,
            1852,
            1900,
            1901,
            2008,
            2009,
            2128,
            2129,
            2130,
            2199,
            2200,
            2221,
            2222,
            2224,
            2225,
            2227,
            2383,
            2385,
            2427,
            2428,
            2528,
            2529,
            2589,
            2590,
            2639,
            2640,
            2673,
            2674,
            2827,
            2828,
            2832,
            2833,
            2834,
            2871,
            2875,
            2883,
            2902,
            2920,
            2921,
            2953,
            2954,
            3002,
            3003,
            3067,
            3073,
            3131,
            3341,
            3348,
            3369,
            3380,
            3385,
            3390,
            3395,
            3400,
            3405,
            3410,
            3415,
            3420,
            3425,
            4049,
            4050,
            4054,
            4059,
            4062,
            4686,
            4687,
            4691,
            4696,
            4697,
            4700,
            5819,
            5831,
            5839,
            5844,
            5867,
            5896,
            5897,
            5899,
            5911,
            5913,
            5916
        ]
    },
    "1024x256": {
        "count": 5,
        "indices": [
            19,
            2478,
            2479,
            2985,
            2987
        ]
    },
    "256x512": {
        "count": 16,
        "indices": [
            23,
            255,
            526,
            646,
            689,
            910,
            1009,
            1375,
            1629,
            2851,
            2853,
            2854,
            4719,
            5921,
            5922,
            5923
        ]
    },
    "256x256": {
        "count": 212,
        "indices": [
            30,
            31,
            32,
            33,
            45,
            47,
            59,
            95,
            99,
            106,
            113,
            129,
            131,
            135,
            136,
            148,
            149,
            158,
            164,
            172,
            206,
            208,
            218,
            226,
            235,
            237,
            239,
            249,
            264,
            268,
            271,
            301,
            303,
            305,
            306,
            334,
            336,
            344,
            345,
            362,
            363,
            387,
            399,
            412,
            413,
            420,
            421,
            426,
            454,
            455,
            472,
            473,
            570,
            572,
            573,
            575,
            579,
            580,
            581,
            589,
            640,
            644,
            670,
            735,
            738,
            739,
            748,
            750,
            757,
            758,
            793,
            850,
            851,
            862,
            887,
            912,
            942,
            943,
            986,
            988,
            991,
            992,
            993,
            996,
            997,
            998,
            999,
            1041,
            1062,
            1063,
            1071,
            1072,
            1077,
            1078,
            1084,
            1085,
            1110,
            1166,
            1167,
            1168,
            1169,
            1170,
            1171,
            1172,
            1223,
            1224,
            1297,
            1301,
            1302,
            1303,
            1355,
            1434,
            1531,
            1563,
            1590,
            1658,
            1661,
            1740,
            1784,
            1853,
            1902,
            1921,
            1975,
            2010,
            2058,
            2069,
            2160,
            2161,
            2162,
            2201,
            2226,
            2286,
            2347,
            2386,
            2387,
            2429,
            2567,
            2591,
            2641,
            2675,
            2767,
            2768,
            2769,
            2770,
            2794,
            2795,
            2797,
            2837,
            2840,
            2841,
            2842,
            2864,
            2865,
            2887,
            2889,
            2890,
            2903,
            2909,
            2912,
            2913,
            2918,
            2922,
            2925,
            2927,
            2931,
            2934,
            2936,
            2955,
            3005,
            3015,
            3050,
            3051,
            3118,
            3136,
            3327,
            3329,
            3360,
            3379,
            3384,
            3389,
            3394,
            3404,
            3409,
            3414,
            3419,
            3424,
            3426,
            3894,
            3895,
            3927,
            4034,
            4071,
            4086,
            4097,
            4681,
            4682,
            4695,
            4701,
            4702,
            4703,
            4821,
            4906,
            5815,
            5842,
            5861,
            5873,
            5874,
            5877,
            5878,
            5879,
            5880,
            5917
        ]
    },
    "384x384": {
        "count": 85,
        "indices": [
            37,
            39,
            41,
            67,
            112,
            139,
            151,
            153,
            161,
            163,
            168,
            175,
            177,
            197,
            198,
            652,
            653,
            654,
            665,
            666,
            714,
            715,
            803,
            804,
            861,
            964,
            1121,
            1196,
            1250,
            1298,
            1299,
            1481,
            1549,
            1551,
            1591,
            1610,
            1611,
            2061,
            2072,
            2073,
            2074,
            2282,
            2284,
            2531,
            2816,
            2817,
            2822,
            2823,
            2835,
            2872,
            2873,
            2891,
            2900,
            2904,
            2910,
            2911,
            2990,
            2991,
            3033,
            3034,
            3381,
            3386,
            3391,
            3396,
            3399,
            3401,
            3406,
            3411,
            3416,
            3421,
            4068,
            4069,
            4070,
            4073,
            4074,
            4075,
            4078,
            4079,
            4083,
            4084,
            4085,
            4090,
            4091,
            4092,
            5893
        ]
    },
    "1024x1024": {
        "count": 43,
        "indices": [
            56,
            57,
            58,
            62,
            64,
            70,
            71,
            73,
            74,
            105,
            176,
            183,
            661,
            987,
            1162,
            1295,
            1391,
            1429,
            1705,
            3008,
            3366,
            3368,
            3371,
            4060,
            5829,
            5830,
            5832,
            5833,
            5834,
            5835,
            5843,
            5845,
            5849,
            5866,
            5870,
            5871,
            5892,
            5894,
            5905,
            5910,
            5912,
            5928,
            5929
        ]
    },
    "512x1024": {
        "count": 2,
        "indices": [
            79,
            80
        ]
    },
    "768x768": {
        "count": 28,
        "indices": [
            103,
            130,
            143,
            146,
            174,
            568,
            963,
            985,
            1117,
            1118,
            1161,
            1294,
            1390,
            1480,
            1948,
            1949,
            2054,
            2055,
            2384,
            3074,
            3359,
            3361,
            3363,
            3367,
            4058,
            4063,
            4693,
            4694
        ]
    },
    "384x393": {
        "count": 2,
        "indices": [
            104,
            110
        ]
    },
    "384x396": {
        "count": 2,
        "indices": [
            108,
            109
        ]
    },
    "512x256": {
        "count": 20,
        "indices": [
            166,
            180,
            535,
            539,
            541,
            577,
            980,
            1270,
            1546,
            2497,
            2820,
            2856,
            2962,
            3374,
            3375,
            4032,
            4038,
            4680,
            5900,
            5901
        ]
    },
    "1024x512": {
        "count": 6,
        "indices": [
            260,
            978,
            1706,
            2855,
            2885,
            4030
        ]
    },
    "640x640": {
        "count": 4,
        "indices": [
            660,
            1428,
            5887,
            5888
        ]
    },
    "512x296": {
        "count": 1,
        "indices": [
            1703
        ]
    },
    "384x256": {
        "count": 1,
        "indices": [
            1704
        ]
    },
    "320x256": {
        "count": 1,
        "indices": [
            2496
        ]
    },
    "768x384": {
        "count": 1,
        "indices": [
            2882
        ]
    },
    "768x512": {
        "count": 4,
        "indices": [
            2924,
            2926,
            4672,
            4674
        ]
    },
    "384x768": {
        "count": 4,
        "indices": [
            2930,
            2932,
            2933,
            2935
        ]
    },
    "256x384": {
        "count": 2,
        "indices": [
            2938,
            2939
        ]
    },
    "256x2048": {
        "count": 2,
        "indices": [
            2999,
            3000
        ]
    },
    "2048x1024": {
        "count": 1,
        "indices": [
            3007
        ]
    },
    "2048x512": {
        "count": 1,
        "indices": [
            3011
        ]
    },
    "956x394": {
        "count": 1,
        "indices": [
            3250
        ]
    },
    "432x256": {
        "count": 1,
        "indices": [
            3251
        ]
    },
    "312x312": {
        "count": 1,
        "indices": [
            3257
        ]
    },
    "240x240": {
        "count": 1,
        "indices": [
            3264
        ]
    },
    "418x212": {
        "count": 1,
        "indices": [
            3288
        ]
    },
    "368x222": {
        "count": 1,
        "indices": [
            3289
        ]
    },
    "768x256": {
        "count": 2,
        "indices": [
            3377,
            4673
        ]
    },
    "600x448": {
        "count": 1,
        "indices": [
            4025
        ]
    },
    "224x320": {
        "count": 2,
        "indices": [
            4717,
            4718
        ]
    },
    "2048x2048": {
        "count": 7,
        "indices": [
            5826,
            5828,
            5836,
            5882,
            5883,
            5908,
            5909
        ]
    },
    "1024x2048": {
        "count": 5,
        "indices": [
            5838,
            5840,
            5855,
            5856,
            5875
        ]
    },
    "512x2048": {
        "count": 2,
        "indices": [
            5852,
            5853
        ]
    },
    "1024x4096": {
        "count": 1,
        "indices": [
            5854
        ]
    },
    "256x1024": {
        "count": 1,
        "indices": [
            5919
        ]
    }
}